Semester III/Digital Design and Computer Organization/Session 02/2_1 MUX.v
module MUX(i, s, y);

input [1:0]i;
input s;
output y;
reg y;

always@(s or i)
begin
case(s)
1'b0: y=i[00];
1'b1: y=i[01];
default: y=0;
endcase
end

endmodule

Semester III/Digital Design and Computer Organization/Session 02/testBench_2_1.v
module TB;

wire yy;
reg [1:0]ii;
reg ss;

initial
begin
$dumpfile("dump.vcd");
$dumpvars(0, TB);
end

MUX newMUX(.i(ii), .s(ss), .y(yy));

initial
begin
ss = 1'b0;
ii = 2'b00;
#5
ii = 2'b01;
#5
ii = 2'b10;
#5
ii = 2'b11;
#5
ss = 1'b1;
ii = 2'b00;
#5
ii = 2'b01;
#5
ii = 2'b10;
#5
ii = 2'b11;
#5
ss = 1'b0;
ii = 2'b00;
end

endmodule

Semester III/Digital Design and Computer Organization/Verilog/DDCO Lab/Session 02/dump.vcd
$date
	Wed Nov 21 13:38:40 2018
$end
$version
	Icarus Verilog
$end
$timescale
	1s
$end
$scope module TB $end
$var wire 1 ! yy $end
$var reg 2 " ii [1:0] $end
$var reg 1 # ss $end
$scope module newMUX $end
$var wire 2 $ i [1:0] $end
$var wire 1 # s $end
$var reg 1 ! y $end
$upscope $end
$upscope $end
$enddefinitions $end
#0
$dumpvars
b0 $
0#
b0 "
0!
$end
#5
1!
b1 "
b1 $
#10
0!
b10 "
b10 $
#15
1!
b11 "
b11 $
#20
0!
b0 "
b0 $
1#
#25
b1 "
b1 $
#30
1!
b10 "
b10 $
#35
b11 "
b11 $
#40
0!
b0 "
b0 $
0#
